py_ha_ws_client/__init__.py
py_ha_ws_client/client.py
py_ha_ws_client-0.7.dist-info/LICENSE
py_ha_ws_client-0.7.dist-info/METADATA
py_ha_ws_client-0.7.dist-info/WHEEL
py_ha_ws_client-0.7.dist-info/top_level.txt
py_ha_ws_client-0.7.dist-info/RECORD
