Metadata-Version: 2.2
Name: py_ha_ws_client
Version: 0.7
Summary: A Python client to make it easy to connect and consume data from the Home Assistant web socket API.
Home-page: https://github.com/designer-living/py-ha-ws-client
Download-URL: https://github.com/designer-living/py-ha-ws-client/archive/0.7.tar.gz
Author: foxy82
Author-email: foxy82.github@gmail.com
License: Apache 2.0
Keywords: Home Assistant,Websocket
Classifier: Development Status :: 4 - Beta
Classifier: Intended Audience :: Developers
Classifier: Topic :: Software Development :: Build Tools
Classifier: License :: OSI Approved :: Apache Software License
Classifier: Programming Language :: Python :: 3.10
License-File: LICENSE
Requires-Dist: ws4py==0.5.1
Dynamic: author
Dynamic: author-email
Dynamic: classifier
Dynamic: description
Dynamic: description-content-type
Dynamic: download-url
Dynamic: home-page
Dynamic: keywords
Dynamic: license
Dynamic: requires-dist
Dynamic: summary
